promptomics/__init__.py
promptomics-0.0.1.dist-info/licenses/LICENSE
promptomics-0.0.1.dist-info/METADATA
promptomics-0.0.1.dist-info/WHEEL
promptomics-0.0.1.dist-info/top_level.txt
promptomics-0.0.1.dist-info/RECORD
