Metadata-Version: 2.4
Name: promptomics
Version: 0.0.1
Summary: The core of Promptomics.com - An open-source lab for prompt engineering and LLM experimentation.
Author-email: promptomics <69essence96@gmail.com>
License: 
Project-URL: Homepage, https://github.com/promptomics/promptomics
Project-URL: Bug Tracker, https://github.com/promptomics/promptomics/issues
Keywords: prompt,prompt engineering,llm,ai,openai,gpt,api
Classifier: Development Status :: 3 - Alpha
Classifier: Intended Audience :: Developers
Classifier: Topic :: Software Development :: Build Tools
Classifier: License :: OSI Approved :: Apache Software License
Classifier: Programming Language :: Python :: 3
Classifier: Programming Language :: Python :: 3.7
Classifier: Programming Language :: Python :: 3.8
Classifier: Programming Language :: Python :: 3.9
Classifier: Programming Language :: Python :: 3.10
Classifier: Programming Language :: Python :: 3.11
Requires-Python: >=3.7
License-File: LICENSE
Dynamic: license-file
